cmsplugin_filer_file/__init__.py
cmsplugin_filer_file/cms_plugins.py
cmsplugin_filer_file/conf.py
cmsplugin_filer_file/forms.py
cmsplugin_filer_file/models.py
cmsplugin_filer_file/tests.py
cmsplugin_filer_file/locale/ca/LC_MESSAGES/django.mo
cmsplugin_filer_file/locale/ca/LC_MESSAGES/django.po
cmsplugin_filer_file/locale/de/LC_MESSAGES/django.mo
cmsplugin_filer_file/locale/de/LC_MESSAGES/django.po
cmsplugin_filer_file/locale/en/LC_MESSAGES/django.mo
cmsplugin_filer_file/locale/en/LC_MESSAGES/django.po
cmsplugin_filer_file/locale/es/LC_MESSAGES/django.mo
cmsplugin_filer_file/locale/es/LC_MESSAGES/django.po
cmsplugin_filer_file/locale/et/LC_MESSAGES/django.mo
cmsplugin_filer_file/locale/et/LC_MESSAGES/django.po
cmsplugin_filer_file/locale/eu/LC_MESSAGES/django.mo
cmsplugin_filer_file/locale/eu/LC_MESSAGES/django.po
cmsplugin_filer_file/locale/fi/LC_MESSAGES/django.mo
cmsplugin_filer_file/locale/fi/LC_MESSAGES/django.po
cmsplugin_filer_file/locale/fr/LC_MESSAGES/django.mo
cmsplugin_filer_file/locale/fr/LC_MESSAGES/django.po
cmsplugin_filer_file/locale/it/LC_MESSAGES/django.mo
cmsplugin_filer_file/locale/it/LC_MESSAGES/django.po
cmsplugin_filer_file/locale/it_IT/LC_MESSAGES/django.mo
cmsplugin_filer_file/locale/it_IT/LC_MESSAGES/django.po
cmsplugin_filer_file/locale/lt/LC_MESSAGES/django.mo
cmsplugin_filer_file/locale/lt/LC_MESSAGES/django.po
cmsplugin_filer_file/locale/lt_LT/LC_MESSAGES/django.mo
cmsplugin_filer_file/locale/lt_LT/LC_MESSAGES/django.po
cmsplugin_filer_file/locale/nb/LC_MESSAGES/django.mo
cmsplugin_filer_file/locale/nb/LC_MESSAGES/django.po
cmsplugin_filer_file/locale/nl/LC_MESSAGES/django.mo
cmsplugin_filer_file/locale/nl/LC_MESSAGES/django.po
cmsplugin_filer_file/locale/nn/LC_MESSAGES/django.mo
cmsplugin_filer_file/locale/nn/LC_MESSAGES/django.po
cmsplugin_filer_file/locale/pl_PL/LC_MESSAGES/django.mo
cmsplugin_filer_file/locale/pl_PL/LC_MESSAGES/django.po
cmsplugin_filer_file/locale/pt_BR/LC_MESSAGES/django.mo
cmsplugin_filer_resurrected-2.1.9.dist-info/AUTHORS
cmsplugin_filer_resurrected-2.1.9.dist-info/LICENSE
cmsplugin_filer_resurrected-2.1.9.dist-info/METADATA
cmsplugin_filer_resurrected-2.1.9.dist-info/WHEEL
cmsplugin_filer_resurrected-2.1.9.dist-info/top_level.txt
cmsplugin_filer_resurrected-2.1.9.dist-info/RECORD
