Metadata-Version: 2.1
Name: cmsplugin-filer-resurrected
Version: 2.1.9
Summary: django-cms plugins for django-filer
Home-page: http://github.com/avryhof/cmsplugin-filer
Author: Stefan Foulis
Author-email: stefan.foulis@gmail.com
License: BSD
Classifier: Development Status :: 5 - Production/Stable
Classifier: Framework :: Django
Classifier: Intended Audience :: Developers
Classifier: License :: OSI Approved :: BSD License
Classifier: Operating System :: OS Independent
Classifier: Programming Language :: Python
Classifier: Topic :: Internet :: WWW/HTTP
License-File: LICENSE
License-File: AUTHORS
Requires-Dist: Django (>1.11)
Requires-Dist: django-filer (>=1.2.0)
Requires-Dist: django-cms (>=3.1)
Requires-Dist: django-sekizai (>=0.4.2)
Requires-Dist: easy-thumbnails (>=1.0)
Requires-Dist: django-appconf
Requires-Dist: djangocms-attributes-field (>=0.1.1)
Requires-Dist: six
